{
  "operationManagement": "Operation Management",
  "operations": "Operations",
  "planManagement": "Plan Management",
  "planArrangements": "Plan Arrangements",
  "planningHistory": "Operation History",
  "clinicManagement": "Clinic Management",
  "personnelManagement":"Personnel Management",
  "plans":"Plans",
  "reports": "Reports",
  "overtimeReport":"Overtime Report",
  "simulation": "Simulation",
  "managementPanel": "Management Panel",
  "users": "Users",
  "feedback": "Feedback",
  "help": "Help",
  "settings": "Settings",
  "definitions": "Definitions",
  "equipments": "Equipments",
  "personnel": "Personnel",
  "operatingRooms": "Operating Rooms",
  "branches": "Branches",
  "PersonnelCategories": "Personnel Categories",
  "PersonnelTitles": "Personnel Title",
  "equipmentTypes": "Equipment Types",
  "operationTypes": "Operation Types",
  "workTypes": "Work Types",
  "youCanManageYourOperations":"You can manage your operations",
  "youCanManageYourPlans":"You can manage your plans",
  "youCanManageYourClinics":"You can manage your clinics",
  "youCanManageYourPersonnels":"You can manage your personnels",
  "changeLanguage":"Change Language"
}
